DotStar_Emulator/manage.py
DotStar_Emulator/__init__.py
DotStar_Emulator/__main__.py
DotStar_Emulator/emulator/app.py
DotStar_Emulator/emulator/config.py
DotStar_Emulator/emulator/entity.py
DotStar_Emulator/emulator/globals.py
DotStar_Emulator/emulator/rate_counter.py
DotStar_Emulator/emulator/scene.py
DotStar_Emulator/emulator/send_test_data.py
DotStar_Emulator/emulator/utils.py
DotStar_Emulator/emulator/vector2.py
DotStar_Emulator/emulator/__init__.py
DotStar_Emulator/emulator/data/mapping_data.py
DotStar_Emulator/emulator/data/strip_data.py
DotStar_Emulator/emulator/data/tcp_reader.py
DotStar_Emulator/emulator/data/__init__.py
DotStar_Emulator/emulator/entities/dotgrid_select.py
DotStar_Emulator/emulator/entities/running_fps.py
DotStar_Emulator/emulator/entities/__init__.py
DotStar_Emulator/emulator/gui/button.py
DotStar_Emulator/emulator/gui/flags.py
DotStar_Emulator/emulator/gui/panels.py
DotStar_Emulator/emulator/gui/text.py
DotStar_Emulator/emulator/gui/widget.py
DotStar_Emulator/emulator/gui/__init__.py
DotStar_Emulator/emulator/init/config.py
DotStar_Emulator/emulator/init/manage.py
DotStar_Emulator/emulator/media/about.txt
DotStar_Emulator/emulator/media/inconsolata-lgc/Inconsolata-LGC.otf
DotStar_Emulator/emulator/media/inconsolata-lgc/LICENSE
DotStar_Emulator/emulator/media/inconsolata-lgc/README
DotStar_Emulator/emulator/scenes/about.py
DotStar_Emulator/emulator/scenes/running.py
DotStar_Emulator/emulator/scenes/__init__.py
DotStar_Emulator/emulator/widgets/color_value.py
DotStar_Emulator/emulator/widgets/dotgrid.py
DotStar_Emulator/emulator/widgets/logo.py
DotStar_Emulator/emulator/widgets/running_info.py
DotStar_Emulator/emulator/widgets/__init__.py
DotStar_Emulator/examples/strandtest.py
DotStar_Emulator/pi/dotstar_pi_spoof.py
DotStar_Emulator/pi/__init__.py
DotStar_Emulator-0.2.dist-info/DESCRIPTION.rst
DotStar_Emulator-0.2.dist-info/METADATA
DotStar_Emulator-0.2.dist-info/metadata.json
DotStar_Emulator-0.2.dist-info/RECORD
DotStar_Emulator-0.2.dist-info/top_level.txt
DotStar_Emulator-0.2.dist-info/WHEEL
