Metadata-Version: 2.0
Name: DotStar-Emulator
Version: 0.2
Summary: DotStar_Emulator is a Adafruit_DotStar LED strip emulator to speed up development of controller software.
Home-page: https://github.com/chrisrossx/DotStar_Emulator
Author: Christopher Ross
Author-email: chris.rossx@gmail.com
License: MIT
Platform: UNKNOWN
Classifier: Development Status :: 4 - Beta
Classifier: License :: OSI Approved :: MIT License
Classifier: Intended Audience :: Developers
Classifier: Environment :: Console
Classifier: Operating System :: OS Independent
Classifier: Topic :: Games/Entertainment
Classifier: Topic :: Multimedia :: Graphics
Classifier: Topic :: System :: Emulators
Requires-Dist: pygame
Requires-Dist: six
Requires-Dist: blinker (>=1.4)
Requires-Dist: pillow (>=2.9.0)
